pokinator/__init__.py
pokinator/pokinator.py
pokinator/tests.py
pokinator/pokemons/__init__.py
pokinator/pokemons/firstgen.py
pokinator-1.1.2.dist-info/DESCRIPTION.rst
pokinator-1.1.2.dist-info/METADATA
pokinator-1.1.2.dist-info/RECORD
pokinator-1.1.2.dist-info/WHEEL
pokinator-1.1.2.dist-info/metadata.json
pokinator-1.1.2.dist-info/top_level.txt
