Metadata-Version: 2.0
Name: pokinator
Version: 1.1.2
Summary: Heroku-like random pokemon name generator for python
Home-page: https://github.com/punkyoon/pokinator
Author: punkyoon
Author-email: punkkid001@gmail.com
License: MIT
Keywords: random pokemon name generator
Platform: any
Classifier: Development Status :: 5 - Production/Stable
Classifier: Intended Audience :: Developers
Classifier: License :: OSI Approved :: MIT License
Classifier: Operating System :: OS Independent
Classifier: Programming Language :: Python
Classifier: Programming Language :: Python :: 3
Classifier: Programming Language :: Python :: 3.4
Classifier: Programming Language :: Python :: 3.5
Classifier: Programming Language :: Python :: 3.6
Classifier: Topic :: Software Development :: Libraries :: Python Modules
